openrouterapi.py
request.py
openrouterapi-0.1.0.dist-info/licenses/LICENSE
openrouterapi-0.1.0.dist-info/METADATA
openrouterapi-0.1.0.dist-info/WHEEL
openrouterapi-0.1.0.dist-info/top_level.txt
openrouterapi-0.1.0.dist-info/RECORD
