Metadata-Version: 2.4
Name: openrouterapi
Version: 0.1.0
Summary: Работа с OpenRouter API
Author-email: Kirill <kirisa49@gmail.com>
Project-URL: HomePage, https://github.com/kirillysz/openrouterapi
Requires-Python: >=3.12
License-File: LICENSE
Requires-Dist: aiohttp>=3.12.15
Dynamic: license-file
